gdbmcp/__init__.py
gdbmcp/__main__.py
gdbmcp/_version.py
gdbmcp/context.py
gdbmcp/main.py
gdbmcp/utils.py
gdbmcp/session/__init__.py
gdbmcp/session/context.py
gdbmcp/session/gdb_session.py
gdbmcp/tools/__init__.py
gdbmcp/tools/command.py
gdbmcp/tools/session.py
gdbmcp_server-0.5.0.dist-info/licenses/LICENSE
gdbmcp_server-0.5.0.dist-info/METADATA
gdbmcp_server-0.5.0.dist-info/WHEEL
gdbmcp_server-0.5.0.dist-info/entry_points.txt
gdbmcp_server-0.5.0.dist-info/top_level.txt
gdbmcp_server-0.5.0.dist-info/RECORD
