Metadata-Version: 2.4
Name: gdbmcp-server
Version: 0.5.0
Summary: GDB mcp server
Maintainer-email: suoyuan <suoyuan666@s5n.xyz>, Neo Xu <neo.xu1990@gmail.com>
License-Expression: Apache-2.0
Project-URL: Source, https://github.com/suoyuanG/gdbmcp
Requires-Python: >=3.10
License-File: LICENSE
Requires-Dist: gdbrpc
Requires-Dist: mcp
Dynamic: license-file
